mqttudp/__init__.py
mqttudp/config.py
mqttudp/engine.py
mqttudp/interlock.py
mqttudp/mqtt_udp_defs.py
mqttudp/openhab.py
mqttudp/rconfig.py
mqttudp/relcom.py
mqttudp2-0.5.post0.dist-info/LICENSE
mqttudp2-0.5.post0.dist-info/METADATA
mqttudp2-0.5.post0.dist-info/WHEEL
mqttudp2-0.5.post0.dist-info/top_level.txt
mqttudp2-0.5.post0.dist-info/RECORD
