Metadata-Version: 2.1
Name: mqttudp2
Version: 0.5.post0
Summary: An MQTT/UDP implementation in Python
Home-page: https://github.com/dzavalishin/mqtt_udp
Author: Dmitry Zavalishin
Author-email: dz@dz.ru
License: UNKNOWN
Platform: UNKNOWN
Classifier: Development Status :: 4 - Beta
Classifier: Environment :: Console
Classifier: Intended Audience :: Developers
Classifier: Operating System :: OS Independent
Classifier: Programming Language :: Python
Classifier: Topic :: Internet
Classifier: Topic :: System :: Networking
